MANIFEST.in
readme.md
setup.py
pymorningstar/__init__.py
pymorningstar/excel.py
pymorningstar/morning_limit.png
pymorningstar.egg-info/PKG-INFO
pymorningstar.egg-info/SOURCES.txt
pymorningstar.egg-info/dependency_links.txt
pymorningstar.egg-info/not-zip-safe
pymorningstar.egg-info/requires.txt
pymorningstar.egg-info/top_level.txt